hvrt/__init__.py
hvrt/adaptive_reducer.py
hvrt/sample_reduction.py
hvrt/selection_strategies.py
hvrt-0.2.0.dist-info/licenses/LICENSE
hvrt-0.2.0.dist-info/METADATA
hvrt-0.2.0.dist-info/WHEEL
hvrt-0.2.0.dist-info/top_level.txt
hvrt-0.2.0.dist-info/RECORD
