Metadata-Version: 2.4
Name: hvrt
Version: 0.2.0
Summary: Hierarchical Variance Reduction Tree (H-VRT) for intelligent sample reduction
Author-email: Jake Peace <mail@jakepeace.me>
License-Expression: MIT
Project-URL: Homepage, https://github.com/hotprotato/hvrt
Project-URL: Documentation, https://github.com/hotprotato/hvrt#readme
Project-URL: Repository, https://github.com/hotprotato/hvrt
Project-URL: Issues, https://github.com/hotprotato/hvrt/issues
Keywords: machine-learning,sample-reduction,data-preprocessing,svm,variance,heavy-tailed
Classifier: Development Status :: 3 - Alpha
Classifier: Intended Audience :: Science/Research
Classifier: Intended Audience :: Developers
Classifier: Programming Language :: Python :: 3
Classifier: Programming Language :: Python :: 3.8
Classifier: Programming Language :: Python :: 3.9
Classifier: Programming Language :: Python :: 3.10
Classifier: Programming Language :: Python :: 3.11
Classifier: Topic :: Scientific/Engineering :: Artificial Intelligence
Requires-Python: >=3.8
License-File: LICENSE
Requires-Dist: numpy>=1.20.0
Requires-Dist: scikit-learn>=1.0.0
Provides-Extra: dev
Requires-Dist: pytest>=7.0.0; extra == "dev"
Requires-Dist: pytest-cov>=3.0.0; extra == "dev"
Requires-Dist: black>=22.0.0; extra == "dev"
Requires-Dist: mypy>=0.950; extra == "dev"
Requires-Dist: twine>=5.0.0; extra == "dev"
Requires-Dist: build>=1.0.0; extra == "dev"
Dynamic: license-file
